odoo/addons/html_text/README.rst
odoo/addons/html_text/__init__.py
odoo/addons/html_text/__manifest__.py
odoo/addons/html_text/i18n/ca.po
odoo/addons/html_text/i18n/de.po
odoo/addons/html_text/i18n/es.po
odoo/addons/html_text/i18n/es_ES.po
odoo/addons/html_text/i18n/it.po
odoo/addons/html_text/i18n/tr.po
odoo/addons/html_text/models/__init__.py
odoo/addons/html_text/models/ir_fields_converter.py
odoo/addons/html_text/static/description/icon.png
odoo/addons/html_text/tests/__init__.py
odoo/addons/html_text/tests/test_extractor.py
odoo11_addon_html_text-11.0.1.0.2.dist-info/DESCRIPTION.rst
odoo11_addon_html_text-11.0.1.0.2.dist-info/METADATA
odoo11_addon_html_text-11.0.1.0.2.dist-info/RECORD
odoo11_addon_html_text-11.0.1.0.2.dist-info/WHEEL
odoo11_addon_html_text-11.0.1.0.2.dist-info/metadata.json
odoo11_addon_html_text-11.0.1.0.2.dist-info/top_level.txt
